LICENCE.md
MANIFEST.in
README.md
setup.py
cmakeast/__init__.py
cmakeast/ast.py
cmakeast/ast_visitor.py
cmakeast/printer.py
cmakeast.egg-info/PKG-INFO
cmakeast.egg-info/SOURCES.txt
cmakeast.egg-info/dependency_links.txt
cmakeast.egg-info/entry_points.txt
cmakeast.egg-info/requires.txt
cmakeast.egg-info/top_level.txt
cmakeast.egg-info/zip-safe
test/test_ast.py
test/test_ast_visitor.py
test/test_print_smoke.py